sqlforerogamer/__init__.py
sqlforerogamer/sqlforerogamer.py
sqlforerogamer-1.3.3.dist-info/DESCRIPTION.rst
sqlforerogamer-1.3.3.dist-info/METADATA
sqlforerogamer-1.3.3.dist-info/RECORD
sqlforerogamer-1.3.3.dist-info/WHEEL
sqlforerogamer-1.3.3.dist-info/metadata.json
sqlforerogamer-1.3.3.dist-info/top_level.txt
