Metadata-Version: 2.0
Name: sqlforerogamer
Version: 1.3.3
Summary: A library for http://erogamescape.dyndns.org/~ap2/ero/toukei_kaiseki/sql_for_erogamer_index.php
Home-page: http://github.com/roronya/sqlforerogamer
Author: roronya
Author-email: roronya628@gmail.com
License: MIT
Keywords: erogame sql
Platform: UNKNOWN
Classifier: Development Status :: 5 - Production/Stable
Classifier: Intended Audience :: Developers
Classifier: Topic :: Software Development :: Libraries
Classifier: License :: OSI Approved :: MIT License
Classifier: Programming Language :: Python :: 3
Requires-Dist: beautifulsoup4
Requires-Dist: html5lib
Requires-Dist: lxml
Requires-Dist: requests
